southwark/__init__.py
southwark/click.py
southwark/config.py
southwark/log.py
southwark/py.typed
southwark/repo.py
southwark/targit.py
southwark-0.9.0.dist-info/LICENSE
southwark-0.9.0.dist-info/METADATA
southwark-0.9.0.dist-info/WHEEL
southwark-0.9.0.dist-info/entry_points.txt
southwark-0.9.0.dist-info/RECORD
