Metadata-Version: 2.1
Name: southwark
Version: 0.9.0
Summary: Extensions to the Dulwich Git library.
Author-email: Dominic Davis-Foster <dominic@davis-foster.co.uk>
License: MIT
Keywords: dulwich,git,vcs
Home-page: https://github.com/repo-helper/southwark
Project-URL: Issue Tracker, https://github.com/repo-helper/southwark/issues
Project-URL: Source Code, https://github.com/repo-helper/southwark
Project-URL: Documentation, https://southwark.readthedocs.io/en/latest
Platform: Windows
Platform: macOS
Platform: Linux
Classifier: Development Status :: 4 - Beta
Classifier: Environment :: Console
Classifier: Intended Audience :: Developers
Classifier: License :: OSI Approved :: MIT License
Classifier: Operating System :: OS Independent
Classifier: Programming Language :: Python
Classifier: Programming Language :: Python :: 3 :: Only
Classifier: Programming Language :: Python :: 3.6
Classifier: Programming Language :: Python :: 3.7
Classifier: Programming Language :: Python :: 3.8
Classifier: Programming Language :: Python :: 3.9
Classifier: Programming Language :: Python :: 3.10
Classifier: Programming Language :: Python :: 3.11
Classifier: Programming Language :: Python :: Implementation :: CPython
Classifier: Programming Language :: Python :: Implementation :: PyPy
Classifier: Topic :: Software Development :: Libraries :: Python Modules
Classifier: Topic :: Software Development :: Version Control :: Git
Classifier: Typing :: Typed
Requires-Python: >=3.6
Requires-Dist: click>=7.1.2
Requires-Dist: consolekit>=0.1.2
Requires-Dist: domdf-python-tools>=2.7.0
Requires-Dist: dulwich!=0.20.7,!=0.20.8,!=0.20.9,>=0.20.5
Requires-Dist: filelock>=3.0.12
Requires-Dist: typing-extensions>=3.7.4.3
